libconsole/__init__.py
libconsole/libconsole.py
libconsole-1.0.0.dist-info/LICENSE
libconsole-1.0.0.dist-info/METADATA
libconsole-1.0.0.dist-info/WHEEL
libconsole-1.0.0.dist-info/top_level.txt
libconsole-1.0.0.dist-info/RECORD
